[{"Production":"Agricultural Production Foodgrains Gram Rabi","Value":"8.83"},{"Production":"Agricultural Production Foodgrains Other Kharif Pulses Rabi","Value":"2.73"},{"Production":"Agricultural Production Foodgrains Pulses","Value":"18.34"},{"Production":"Agricultural Production Foodgrains Pulses Kharif","Value":"5.91"},{"Production":"Agricultural Production Foodgrains Pulses Rabi","Value":"12.43"},{"Production":"Agricultural Production Major Crops Target Foodgrains","Value":"254.24"},{"Production":"Agricultural Production Major Crops Achievements Foodgrains","Value":"255.36"},{"Production":"Agriculture Production Foodgrains Area 5 Yr Avg Foodgrains Total","Value":"NA"},{"Production":"Agriculture Production Foodgrains Area 5 Yr Avg Foodgrains Kharif","Value":"NA"},{"Production":"Agriculture Production Foodgrains Area 5 Yr Avg Foodgrains Rabi","Value":"NA"},{"Production":"Agriculture Production Foodgrains Area 5 Yr Avg Foodgrains Coarse Cereals Total","Value":"NA"},{"Production":"Agriculture Production Foodgrains Area 5 Yr Avg Foodgrains Coarse Cereals Kharif","Value":"NA"},{"Production":"Agriculture Production Foodgrains Area 5 Yr Avg Foodgrains Coarse Cereals Rabi","Value":"NA"},{"Production":"Agriculture Production Foodgrains Area 5 Yr Avg Foodgrains Coarse Cereals Rice Total","Value":"NA"},{"Production":"Agricultural Production Foodgrains Area 5 Yr Avg Foodgrains Coarse Cereals Rice Kharif","Value":"NA"},{"Production":"Agriculture Production Foodgrains Area 5 Yr Avg Foodgrains Coarse Cereals Rice Rabi","Value":"NA"},{"Production":"Agriculture Production Foodgrains Area 5 Yr Avg Foodgrains Coarse Cereals Wheat Rabi","Value":"NA"},{"Production":"Agriculture Production Foodgrains Area 5 Yr Avg Foodgrains Coarse Cereals Jowar Total","Value":"NA"},{"Production":"Agriculture Production Foodgrains Area 5 Yr Avg Foodgrains Coarse Cereals Jowar Kharif","Value":"NA"},{"Production":"Agriculture Production Foodgrains Area 5 Yr Avg Foodgrains Coarse Cereals Jowar Rabi","Value":"NA"},{"Production":"Agriculture Production Foodgrains Area 5 Yr Avg Foodgrains Coarse Cereals Bajra Kharif","Value":"NA"},{"Production":"Agriculture Production Foodgrains Area 5 Yr Avg Foodgrains Coarse Cereals Maize Total","Value":"NA"},{"Production":"Agriculture Production Foodgrains Area 5 Yr Avg Foodgrains Coarse Cereals Maize Kharif","Value":"NA"},{"Production":"Agriculture Production Foodgrains Area 5 Yr Avg Foodgrains Coarse Cereals Maize Rabi","Value":"NA"},{"Production":"Agriculture Production Foodgrains Area 5 Yr Avg Foodgrains Pulses Total","Value":"NA"},{"Production":"Agriculture Production Foodgrains Area 5 Yr Avg Foodgrains Pulses Kharif","Value":"NA"},{"Production":"Agriculture Production Foodgrains Area 5 Yr Avg Foodgrains Pulses Rabi","Value":"NA"},{"Production":"Agriculture Production Foodgrains Area 5 Yr Avg Foodgrains Pulses Tur Kharif","Value":"NA"},{"Production":"Agriculture Production Foodgrains Area 5 Yr Avg Foodgrains Pulses Gram Rabi","Value":"NA"},{"Production":"Agriculture Production Foodgrains Area 5 Yr Avg Oilseeds Nine Oilseeds","Value":"NA"},{"Production":"Agriculture Production Foodgrains Area 5 Yr Avg Oilseeds Nine Oilseeds Groundnut","Value":"NA"},{"Production":"Agriculture Production Foodgrains Area 5 Yr Avg Oilseeds Nine Oilseeds Rapeseed and Mustard Rabi","Value":"NA"},{"Production":"Agriculture Production Foodgrains Area 5 Yr Avg Oilseeds Nine Oilseeds Soyabean Kharif","Value":"NA"},{"Production":"Agriculture Production Foodgrains Area 5 Yr Avg Oilseeds Nine Oilseeds Sunflower","Value":"NA"},{"Production":"Agriculture Production Foodgrains Area 5 Yr Avg Other Cash Crops Cotton","Value":"NA"},{"Production":"Agriculture Production Foodgrains Area 5 Yr Avg Other Cash Crops Jute and Mesta","Value":"NA"},{"Production":"Agriculture Production Foodgrains Area 5 Yr Avg Other Cash Crops Onion","Value":"NA"},{"Production":"Agriculture Production Foodgrains Area 5 Yr Avg Other Cash Crops Potato","Value":"NA"},{"Production":"Agriculture Production Foodgrains Area 5 Yr Avg Other Cash Crops Sugarcane","Value":"NA"},{"Production":"Agriculture Production Foodgrains Production Foodgrains Total","Value":"NA"},{"Production":"Agriculture Production Foodgrains Production Foodgrains Kharif","Value":"NA"},{"Production":"Agriculture Production Foodgrains Production Foodgrains Rabi","Value":"NA"},{"Production":"Agriculture Production Foodgrains Production Foodgrains Coarse Cereals Total","Value":"NA"},{"Production":"Agriculture Production Foodgrains Production Foodgrains Coarse Cereals Kharif","Value":"NA"},{"Production":"Agriculture Production Foodgrains Production Foodgrains Coarse Cereals Rabi","Value":"NA"},{"Production":"Agriculture Production Foodgrains Production Foodgrains Coarse Cereals Rice Total","Value":"NA"},{"Production":"Agricultural Production Foodgrains Production Foodgrains Coarse Cereals Rice Kharif","Value":"NA"},{"Production":"Agriculture Production Foodgrains Production Foodgrains Coarse Cereals Rice Rabi","Value":"NA"},{"Production":"Agriculture Production Foodgrains Production Foodgrains Coarse Cereals Wheat Rabi","Value":"NA"},{"Production":"Agriculture Production Foodgrains Production Foodgrains Coarse Cereals Jowar Total","Value":"NA"},{"Production":"Agriculture Production Foodgrains Production Foodgrains Coarse Cereals Jowar Kharif","Value":"NA"},{"Production":"Agriculture Production Foodgrains Production Foodgrains Coarse Cereals Jowar Rabi","Value":"NA"},{"Production":"Agriculture Production Foodgrains Production Foodgrains Coarse Cereals Bajra Kharif","Value":"NA"},{"Production":"Agriculture Production Foodgrains Production Foodgrains Coarse Cereals Maize Total","Value":"NA"},{"Production":"Agriculture Production Foodgrains Production Foodgrains Coarse Cereals Maize Kharif","Value":"NA"},{"Production":"Agriculture Production Foodgrains Production Foodgrains Coarse Cereals Maize Rabi","Value":"NA"},{"Production":"Agriculture Production Foodgrains Production Foodgrains Pulses Total","Value":"NA"},{"Production":"Agriculture Production Foodgrains Production Foodgrains Pulses Tur Kharif","Value":"NA"},{"Production":"Agriculture Production Foodgrains Production Foodgrains Pulses Gram Rabi","Value":"NA"},{"Production":"Agriculture Production Foodgrains Production Foodgrains Pulses Kharif","Value":"NA"},{"Production":"Agriculture Production Foodgrains Production Foodgrains Pulses Rabi","Value":"NA"},{"Production":"Agriculture Production Foodgrains Production Oilseeds Nine Oilseeds","Value":"NA"},{"Production":"Agriculture Production Foodgrains Production Oilseeds Nine Oilseeds Groundnut","Value":"NA"},{"Production":"Agriculture Production Foodgrains Production Oilseeds Nine Oilseeds Rapeseed and Mustard Rabi","Value":"NA"},{"Production":"Agriculture Production Foodgrains Production Oilseeds Nine Oilseeds Soyabean Kharif","Value":"NA"},{"Production":"Agriculture Production Foodgrains Production Oilseeds Nine Oilseeds Sunflower","Value":"NA"},{"Production":"Agriculture Production Foodgrains Production Other Cash Crops Cotton","Value":"NA"},{"Production":"Agriculture Production Foodgrains Production Other Cash Crops Jute and Mesta","Value":"NA"},{"Production":"Agriculture Production Foodgrains Production Other Cash Crops Onion","Value":"NA"},{"Production":"Agriculture Production Foodgrains Production Other Cash Crops Potato","Value":"NA"},{"Production":"Agriculture Production Foodgrains Production Other Cash Crops Sugarcane","Value":"NA"},{"Production":"Agriculture Production Foodgrains Yield Foodgrains Total","Value":"NA"},{"Production":"Agriculture Production Foodgrains Yield Foodgrains Kharif","Value":"NA"},{"Production":"Agriculture Production Foodgrains Yield Foodgrains Rabi","Value":"NA"},{"Production":"Agriculture Production Foodgrains Yield Foodgrains Coarse Cereals Total","Value":"NA"},{"Production":"Agriculture Production Foodgrains Yield Foodgrains Coarse Cereals Kharif","Value":"NA"},{"Production":"Agriculture Production Foodgrains Yield Foodgrains Coarse Cereals Rabi","Value":"NA"},{"Production":"Agriculture Production Foodgrains Yield Foodgrains Coarse Cereals Rice Total","Value":"NA"},{"Production":"Agricultural Production Foodgrains Yield Foodgrains Coarse Cereals Rice Kharif","Value":"NA"},{"Production":"Agriculture Production Foodgrains Yield Foodgrains Coarse Cereals Rice Rabi","Value":"NA"},{"Production":"Agriculture Production Foodgrains Yield Foodgrains Coarse Cereals Wheat Rabi","Value":"NA"},{"Production":"Agriculture Production Foodgrains Yield Foodgrains Coarse Cereals Jowar Total","Value":"NA"},{"Production":"Agriculture Production Foodgrains Yield Foodgrains Coarse Cereals Jowar Kharif","Value":"NA"},{"Production":"Agriculture Production Foodgrains Yield Foodgrains Coarse Cereals Jowar Rabi","Value":"NA"},{"Production":"Agriculture Production Foodgrains Yield Foodgrains Coarse Cereals Bajra Kharif","Value":"NA"},{"Production":"Agriculture Production Foodgrains Yield Foodgrains Coarse Cereals Maize Total","Value":"NA"},{"Production":"Agriculture Production Foodgrains Yield Foodgrains Coarse Cereals Maize Kharif","Value":"NA"},{"Production":"Agriculture Production Foodgrains Yield Foodgrains Coarse Cereals Maize Rabi","Value":"NA"},{"Production":"Agriculture Production Foodgrains Yield Foodgrains Pulses Total","Value":"NA"},{"Production":"Agriculture Production Foodgrains Yield Foodgrains Pulses Kharif","Value":"NA"},{"Production":"Agriculture Production Foodgrains Yield Foodgrains Pulses Rabi","Value":"NA"},{"Production":"Agriculture Production Foodgrains Yield Foodgrains Pulses Tur Kharif","Value":"NA"},{"Production":"Agriculture Production Foodgrains Yield Foodgrains Pulses Gram Rabi","Value":"NA"},{"Production":"Agriculture Production Foodgrains Yield Oilseeds Nine Oilseeds","Value":"NA"},{"Production":"Agriculture Production Foodgrains Yield Oilseeds Nine Oilseeds Groundnut","Value":"NA"},{"Production":"Agriculture Production Foodgrains Yield Oilseeds Nine Oilseeds Rapeseed and Mustard Rabi","Value":"NA"},{"Production":"Agriculture Production Foodgrains Yield Oilseeds Nine Oilseeds Soyabean Kharif","Value":"NA"},{"Production":"Agriculture Production Foodgrains Yield Oilseeds Nine Oilseeds Sunflower","Value":"NA"},{"Production":"Agriculture Production Foodgrains Yield Other Cash Crops Cotton","Value":"NA"},{"Production":"Agriculture Production Foodgrains Yield Other Cash Crops Jute and Mesta","Value":"NA"},{"Production":"Agriculture Production Foodgrains Yield Other Cash Crops Onion","Value":"NA"},{"Production":"Agriculture Production Foodgrains Yield Other Cash Crops Potato","Value":"NA"},{"Production":"Agriculture Production Foodgrains Yield Other Cash Crops Sugarcane","Value":"NA"},{"Production":"Agricultural Production Foodgrains Area Andhra Pradesh","Value":"6.85"},{"Production":"Agricultural Production Foodgrains Area Assam","Value":"2.52"},{"Production":"Agricultural Production Foodgrains Area Bihar","Value":"6.71"},{"Production":"Agricultural Production Foodgrains Area Chhattisgarh","Value":"5.04"},{"Production":"Agricultural Production Foodgrains Area Gujarat","Value":"3.68"},{"Production":"Agricultural Production Foodgrains Area Haryana","Value":"4.39"},{"Production":"Agricultural Production Foodgrains Area Jharkhand","Value":"2.31"},{"Production":"Agricultural Production Foodgrains Area Karnataka","Value":"7.42"},{"Production":"Agricultural Production Foodgrains Area Madhya Pradesh","Value":"14.13"},{"Production":"Agricultural Production Foodgrains Area Maharashtra","Value":"10.11"},{"Production":"Agricultural Production Foodgrains Area Orissa","Value":"5.04"},{"Production":"Agricultural Production Foodgrains Area Punjab","Value":"6.59"},{"Production":"Agricultural Production Foodgrains Area Rajasthan","Value":"12.17"},{"Production":"Agricultural Production Foodgrains Area Tamil Nadu","Value":"2.89"},{"Production":"Agricultural Production Foodgrains Area Uttar Pradesh","Value":"19.96"},{"Production":"Agricultural Production Foodgrains Area Uttaranchal","Value":"0.93"},{"Production":"Agricultural Production Foodgrains Area West Bengal","Value":"6.09"},{"Production":"Agricultural Production Foodgrains Area Others","Value":"3.33"},{"Production":"Agricultural Production Foodgrains Volume Andhra Pradesh","Value":"17.93"},{"Production":"Agricultural Production Foodgrains Volume Assam","Value":"4.76"},{"Production":"Agricultural Production Foodgrains Volume Bihar","Value":"15.62"},{"Production":"Agricultural Production Foodgrains Volume Chhattisgarh","Value":"7.63"},{"Production":"Agricultural Production Foodgrains Volume Gujarat","Value":"7.32"},{"Production":"Agricultural Production Foodgrains Volume Haryana","Value":"16.22"},{"Production":"Agricultural Production Foodgrains Volume Jharkhand","Value":"4.3"},{"Production":"Agricultural Production Foodgrains Volume Karnataka","Value":"10.93"},{"Production":"Agricultural Production Foodgrains Volume Madhya Pradesh","Value":"23.42"},{"Production":"Agricultural Production Foodgrains Volume Maharashtra","Value":"10.69"},{"Production":"Agricultural Production Foodgrains Volume Orissa","Value":"8.35"},{"Production":"Agricultural Production Foodgrains Volume Punjab","Value":"28.07"},{"Production":"Agricultural Production Foodgrains Volume Rajasthan","Value":"18.03"},{"Production":"Agricultural Production Foodgrains Volume Tamil Nadu","Value":"6.29"},{"Production":"Agricultural Production Foodgrains Volume Uttar Pradesh","Value":"50.84"},{"Production":"Agricultural Production Foodgrains Volume Uttaranchal","Value":"1.8"},{"Production":"Agricultural Production Foodgrains Volume West Bengal","Value":"16.51"},{"Production":"Agricultural Production Foodgrains Volume Others","Value":"6.64"},{"Production":"Agricultural Production Foodgrains Yield Andhra Pradesh","Value":"2616"},{"Production":"Agricultural Production Foodgrains Yield Assam","Value":"1889"},{"Production":"Agricultural Production Foodgrains Yield Bihar","Value":"2329"},{"Production":"Agricultural Production Foodgrains Yield Chhattisgarh","Value":"1514"},{"Production":"Agricultural Production Foodgrains Yield Gujarat","Value":"1990"},{"Production":"Agricultural Production Foodgrains Yield Haryana","Value":"3698"},{"Production":"Agricultural Production Foodgrains Yield Jharkhand","Value":"1861"},{"Production":"Agricultural Production Foodgrains Yield Karnataka","Value":"1472"},{"Production":"Agricultural Production Foodgrains Yield Madhya Pradesh","Value":"1657"},{"Production":"Agricultural Production Foodgrains Yield Maharashtra","Value":"1057"},{"Production":"Agricultural Production Foodgrains Yield Orissa","Value":"1658"},{"Production":"Agricultural Production Foodgrains Yield Punjab","Value":"4258"},{"Production":"Agricultural Production Foodgrains Yield Rajasthan","Value":"1482"},{"Production":"Agricultural Production Foodgrains Yield Tamil Nadu","Value":"2175"},{"Production":"Agricultural Production Foodgrains Yield Uttar Pradesh","Value":"2547"},{"Production":"Agricultural Production Foodgrains Yield Uttaranchal","Value":"1939"},{"Production":"Agricultural Production Foodgrains Yield West Bengal","Value":"2711"},{"Production":"Agricultural Production Foodgrains Rice Area","Value":"42.8"},{"Production":"Agricultural Production Foodgrains Rice Volume","Value":"104.4"},{"Production":"Agricultural Production Foodgrains Rice Yield","Value":"2462"},{"Production":"Agricultural Production Foodgrains Rice Area Andhra Pradesh","Value":"3.49"},{"Production":"Agricultural Production Foodgrains Rice Area Assam","Value":"2.24"},{"Production":"Agricultural Production Foodgrains Rice Area Bihar","Value":"3.25"},{"Production":"Agricultural Production Foodgrains Rice Area Chhattisgarh","Value":"3.78"},{"Production":"Agricultural Production Foodgrains Rice Area Gujarat","Value":"0.7"},{"Production":"Agricultural Production Foodgrains Rice Area Haryana","Value":"1.22"},{"Production":"Agricultural Production Foodgrains Rice Area Jharkland","Value":"1.35"},{"Production":"Agricultural Production Foodgrains Rice Area Karnataka","Value":"1.27"},{"Production":"Agricultural Production Foodgrains Rice Area Kerala","Value":"0.2"},{"Production":"Agricultural Production Foodgrains Rice Area Madhya Pradesh","Value":"1.88"},{"Production":"Agricultural Production Foodgrains Rice Area Maharashtra","Value":"1.55"},{"Production":"Agricultural Production Foodgrains Rice Area Orissa","Value":"4.03"},{"Production":"Agricultural Production Foodgrains Rice Area Punjab","Value":"2.85"},{"Production":"Agricultural Production Foodgrains Rice Area Tamil Nadu","Value":"1.58"},{"Production":"Agricultural Production Foodgrains Rice Area Uttar Pradesh","Value":"5.86"},{"Production":"Agricultural Production Foodgrains Rice Area West Bengal","Value":"5.43"},{"Production":"Agricultural Production Foodgrains Rice Area Others","Value":"1.73"},{"Production":"Agricultural Production Foodgrains Rice Volume Andhra Pradesh","Value":"10910"},{"Production":"Agricultural Production Foodgrains Rice Volume Arunachal Pradesh","Value":"NA"},{"Production":"Agricultural Production Foodgrains Rice Volume Assam","Value":"4560"},{"Production":"Agricultural Production Foodgrains Rice Volume Bihar","Value":"7340"},{"Production":"Agricultural Production Foodgrains Rice Volume Chhattisgarh","Value":"6610"},{"Production":"Agricultural Production Foodgrains Rice Volume Goa","Value":"NA"},{"Production":"Agricultural Production Foodgrains Rice Volume Gujarat","Value":"1500"},{"Production":"Agricultural Production Foodgrains Rice Volume Haryana","Value":"3980"},{"Production":"Agricultural Production Foodgrains Rice Volume Himachal Pradesh","Value":"134.3"},{"Production":"Agricultural Production Foodgrains Rice Volume Jammu and Kashmir","Value":"545.6"},{"Production":"Agricultural Production Foodgrains Rice Volume Jharkhand","Value":"3030"},{"Production":"Agricultural Production Foodgrains Rice Volume Karnataka","Value":"3280"},{"Production":"Agricultural Production Foodgrains Rice Volume Kerala","Value":"530"},{"Production":"Agricultural Production Foodgrains Rice Volume Madhya Pradesh","Value":"2780"},{"Production":"Agricultural Production Foodgrains Rice Volume Maharashtra","Value":"3040"},{"Production":"Agricultural Production Foodgrains Rice Volume Manipur","Value":"NA"},{"Production":"Agricultural Production Foodgrains Rice Volume Meghalaya","Value":"NA"},{"Production":"Agricultural Production Foodgrains Rice Volume Mizoram","Value":"NA"},{"Production":"Agricultural Production Foodgrains Rice Volume Nagaland","Value":"NA"},{"Production":"Agricultural Production Foodgrains Rice Volume Orissa","Value":"7640"},{"Production":"Agricultural Production Foodgrains Rice Volume Punjab","Value":"11370"},{"Production":"Agricultural Production Foodgrains Rice Volume Rajasthan","Value":"222.5"},{"Production":"Agricultural Production Foodgrains Rice Volume Sikkim","Value":"NA"},{"Production":"Agricultural Production Foodgrains Rice Volume Tamil Nadu","Value":"4400"},{"Production":"Agricultural Production Foodgrains Rice Volume Tripura","Value":"NA"},{"Production":"Agricultural Production Foodgrains Rice Volume Union Territories","Value":"NA"},{"Production":"Agricultural Production Foodgrains Rice Volume Uttar Pradesh","Value":"14410"},{"Production":"Agricultural Production Foodgrains Rice Volume Uttaranchal","Value":"581"},{"Production":"Agricultural Production Foodgrains Rice Volume West Bengal","Value":"14960"},{"Production":"Agricultural Production Foodgrains Rice Yield Andhra Pradesh","Value":"3126"},{"Production":"Agricultural Production Foodgrains Rice Yield Assam","Value":"2036"},{"Production":"Agricultural Production Foodgrains Rice Yield Bihar","Value":"2258"},{"Production":"Agricultural Production Foodgrains Rice Yield Chhattisgarh","Value":"1749"},{"Production":"Agricultural Production Foodgrains Rice Yield Gujarat","Value":"2143"},{"Production":"Agricultural Production Foodgrains Rice Yield Haryana","Value":"3262"},{"Production":"Agricultural Production Foodgrains Rice Yield Jharkland","Value":"2244"},{"Production":"Agricultural Production Foodgrains Rice Yield Karnataka","Value":"2583"},{"Production":"Agricultural Production Foodgrains Rice Yield Kerala","Value":"2650"},{"Production":"Agricultural Production Foodgrains Rice Yield Madhya Pradesh","Value":"1479"},{"Production":"Agricultural Production Foodgrains Rice Yield Maharashtra","Value":"1961"},{"Production":"Agricultural Production Foodgrains Rice Yield Orissa","Value":"1896"},{"Production":"Agricultural Production Foodgrains Rice Yield Punjab","Value":"3989"},{"Production":"Agricultural Production Foodgrains Rice Yield Tamil Nadu","Value":"2785"},{"Production":"Agricultural Production Foodgrains Rice Yield Uttar Pradesh","Value":"2459"},{"Production":"Agricultural Production Foodgrains Rice Yield West Bengal","Value":"2755"},{"Production":"Agricultural Production Foodgrains Wheat Area","Value":"30"},{"Production":"Agricultural Production Foodgrains Wheat Volume","Value":"92.46"},{"Production":"Agricultural Production Foodgrains Wheat Yield","Value":"3117"},{"Production":"Agricultural Production Foodgrains Wheat Area Assam","Value":"0.05"},{"Production":"Agricultural Production Foodgrains Wheat Area Bihar","Value":"2.22"},{"Production":"Agricultural Production Foodgrains Wheat Area Gujarat","Value":"1.05"},{"Production":"Agricultural Production Foodgrains Wheat Area Haryana","Value":"2.5"},{"Production":"Agricultural Production Foodgrains Wheat Area Himachal Pradesh","Value":"0.36"},{"Production":"Agricultural Production Foodgrains Wheat Area Jammu and Kashmir","Value":"0.3"},{"Production":"Agricultural Production Foodgrains Wheat Area Jharkhand","Value":"0.16"},{"Production":"Agricultural Production Foodgrains Wheat Area Karnataka","Value":"0.23"},{"Production":"Agricultural Production Foodgrains Wheat Area Madhya Pradesh","Value":"5.3"},{"Production":"Agricultural Production Foodgrains Wheat Area Maharashtra","Value":"0.59"},{"Production":"Agricultural Production Foodgrains Wheat Area Punjab","Value":"3.52"},{"Production":"Agricultural Production Foodgrains Wheat Area Rajasthan","Value":"2.82"},{"Production":"Agricultural Production Foodgrains Wheat Area Uttar Pradesh","Value":"9.73"},{"Production":"Agricultural Production Foodgrains Wheat Area Uttaranchal","Value":"0.36"},{"Production":"Agricultural Production Foodgrains Wheat Area West Bengal","Value":"0.32"},{"Production":"Agricultural Production Foodgrains Wheat Area Others","Value":"0.14"},{"Production":"Agricultural Production Foodgrains Wheat Volume Arunachal Pradesh","Value":"NA"},{"Production":"Agricultural Production Foodgrains Wheat Volume Assam","Value":"60"},{"Production":"Agricultural Production Foodgrains Wheat Volume Bihar","Value":"5380"},{"Production":"Agricultural Production Foodgrains Wheat Volume Chhattisgarh","Value":"141.3"},{"Production":"Agricultural Production Foodgrains Wheat Volume Goa","Value":"NA"},{"Production":"Agricultural Production Foodgrains Wheat Volume Gujarat","Value":"3140"},{"Production":"Agricultural Production Foodgrains Wheat Volume Haryana","Value":"11120"},{"Production":"Agricultural Production Foodgrains Wheat Volume Himachal Pradesh","Value":"540"},{"Production":"Agricultural Production Foodgrains Wheat Volume Jammu and Kashmir","Value":"420"},{"Production":"Agricultural Production Foodgrains Wheat Volume Jharkhand","Value":"270"},{"Production":"Agricultural Production Foodgrains Wheat Volume Karnataka","Value":"170"},{"Production":"Agricultural Production Foodgrains Wheat Volume Kerala","Value":"NA"},{"Production":"Agricultural Production Foodgrains Wheat Volume Madhya Pradesh","Value":"13130"},{"Production":"Agricultural Production Foodgrains Wheat Volume Maharashtra","Value":"880"},{"Production":"Agricultural Production Foodgrains Wheat Volume Manipur","Value":"NA"},{"Production":"Agricultural Production Foodgrains Wheat Volume Meghalaya","Value":"NA"},{"Production":"Agricultural Production Foodgrains Wheat Volume Mizoram","Value":"NA"},{"Production":"Agricultural Production Foodgrains Wheat Volume Nagaland","Value":"NA"},{"Production":"Agricultural Production Foodgrains Wheat Volume Orissa","Value":"2.1"},{"Production":"Agricultural Production Foodgrains Wheat Volume Punjab","Value":"16110"},{"Production":"Agricultural Production Foodgrains Wheat Volume Rajasthan","Value":"8950"},{"Production":"Agricultural Production Foodgrains Wheat Volume Sikkim","Value":"NA"},{"Production":"Agricultural Production Foodgrains Wheat Volume Tamil Nadu","Value":"NA"},{"Production":"Agricultural Production Foodgrains Wheat Volume Tripura","Value":"NA"},{"Production":"Agricultural Production Foodgrains Wheat Volume Union Territories","Value":"NA"},{"Production":"Agricultural Production Foodgrains Wheat Volume Uttar Pradesh","Value":"30300"},{"Production":"Agricultural Production Foodgrains Wheat Volume Uttaranchal","Value":"840"},{"Production":"Agricultural Production Foodgrains Wheat Volume West Bengal","Value":"910"},{"Production":"Agricultural Production Foodgrains Wheat Yield Assam","Value":"1188"},{"Production":"Agricultural Production Foodgrains Wheat Yield Bihar","Value":"2427"},{"Production":"Agricultural Production Foodgrains Wheat Yield Gujarat","Value":"2986"},{"Production":"Agricultural Production Foodgrains Wheat Yield Haryana","Value":"4452"},{"Production":"Agricultural Production Foodgrains Wheat Yield Himachal Pradesh","Value":"1514"},{"Production":"Agricultural Production Foodgrains Wheat Yield Jammu and Kashmir","Value":"1404"},{"Production":"Agricultural Production Foodgrains Wheat Yield Jharkhand","Value":"1716"},{"Production":"Agricultural Production Foodgrains Wheat Yield Karnataka","Value":"735"},{"Production":"Agricultural Production Foodgrains Wheat Yield Madhya Pradesh","Value":"2478"},{"Production":"Agricultural Production Foodgrains Wheat Yield Maharashtra","Value":"1473"},{"Production":"Agricultural Production Foodgrains Wheat Yield Punjab","Value":"4573"},{"Production":"Agricultural Production Foodgrains Wheat Yield Rajasthan","Value":"3175"},{"Production":"Agricultural Production Foodgrains Wheat Yield Uttar Pradesh","Value":"3113"},{"Production":"Agricultural Production Foodgrains Wheat Yield Uttaranchal","Value":"2341"},{"Production":"Agricultural Production Foodgrains Wheat Yield West Bengal","Value":"2817"},{"Production":"Agricultural Production Foodgrains Coarse Cereals Area","Value":"24.8"},{"Production":"Agricultural Production Foodgrains Coarse Cereals Volume","Value":"40.08"},{"Production":"Agricultural Production Foodgrains Coarse Cereals Yield","Value":"1626"},{"Production":"Agricultural Production Foodgrains Coarse Cereals Area Andhra Pradesh","Value":"1.41"},{"Production":"Agricultural Production Foodgrains Coarse Cereals Area Bihar","Value":"0.72"},{"Production":"Agricultural Production Foodgrains Coarse Cereals Area Chhattisgarh","Value":"0.26"},{"Production":"Agricultural Production Foodgrains Coarse Cereals Area Gujarat","Value":"1.25"},{"Production":"Agricultural Production Foodgrains Coarse Cereals Area Haryana","Value":"0.52"},{"Production":"Agricultural Production Foodgrains Coarse Cereals Area Himachal Pradesh","Value":"0.31"},{"Production":"Agricultural Production Foodgrains Coarse Cereals Area Jammu and Kashmir","Value":"0.35"},{"Production":"Agricultural Production Foodgrains Coarse Cereals Area Jharkhand","Value":"0.25"},{"Production":"Agricultural Production Foodgrains Coarse Cereals Area Karnataka","Value":"3.59"},{"Production":"Agricultural Production Foodgrains Coarse Cereals Area Madhya Pradesh","Value":"1.64"},{"Production":"Agricultural Production Foodgrains Coarse Cereals Area Maharashtra","Value":"4.69"},{"Production":"Agricultural Production Foodgrains Coarse Cereals Area Orissa","Value":"0.18"},{"Production":"Agricultural Production Foodgrains Coarse Cereals Area Punjab","Value":"0.15"},{"Production":"Agricultural Production Foodgrains Coarse Cereals Area Rajasthan","Value":"5.98"},{"Production":"Agricultural Production Foodgrains Coarse Cereals Area Tamil Nadu","Value":"0.7"},{"Production":"Agricultural Production Foodgrains Coarse Cereals Area Uttar Pradesh","Value":"2"},{"Production":"Agricultural Production Foodgrains Coarse Cereals Area Uttaranchal","Value":"0.25"},{"Production":"Agricultural Production Foodgrains Coarse Cereals Area West Bengal","Value":"0.12"},{"Production":"Agricultural Production Foodgrains Coarse Cereals Area Others","Value":"0.27"},{"Production":"Agricultural Production Foodgrains Coarse Cereals Volume Andhra Pradesh","Value":"5440"},{"Production":"Agricultural Production Foodgrains Coarse Cereals Volume Arunachal Pradesh","Value":"NA"},{"Production":"Agricultural Production Foodgrains Coarse Cereals Volume Assam","Value":"17"},{"Production":"Agricultural Production Foodgrains Coarse Cereals Volume Bihar","Value":"2370"},{"Production":"Agricultural Production Foodgrains Coarse Cereals Volume Chhattisgarh","Value":"240"},{"Production":"Agricultural Production Foodgrains Coarse Cereals Volume Goa","Value":"NA"},{"Production":"Agricultural Production Foodgrains Coarse Cereals Volume Gujarat","Value":"2070"},{"Production":"Agricultural Production Foodgrains Coarse Cereals Volume Haryana","Value":"1000"},{"Production":"Agricultural Production Foodgrains Coarse Cereals Volume Himachal Pradesh","Value":"670"},{"Production":"Agricultural Production Foodgrains Coarse Cereals Volume Jammu and Kashmir","Value":"540"},{"Production":"Agricultural Production Foodgrains Coarse Cereals Volume Jharkhand","Value":"410"},{"Production":"Agricultural Production Foodgrains Coarse Cereals Volume Karnataka","Value":"6150"},{"Production":"Agricultural Production Foodgrains Coarse Cereals Volume Kerala","Value":"0.3"},{"Production":"Agricultural Production Foodgrains Coarse Cereals Volume Madhya Pradesh","Value":"2530"},{"Production":"Agricultural Production Foodgrains Coarse Cereals Volume Maharashtra","Value":"4360"},{"Production":"Agricultural Production Foodgrains Coarse Cereals Volume Manipur","Value":"NA"},{"Production":"Agricultural Production Foodgrains Coarse Cereals Volume Meghalaya","Value":"NA"},{"Production":"Agricultural Production Foodgrains Coarse Cereals Volume Mizoram","Value":"NA"},{"Production":"Agricultural Production Foodgrains Coarse Cereals Volume Nagaland","Value":"NA"},{"Production":"Agricultural Production Foodgrains Coarse Cereals Volume Orissa","Value":"290"},{"Production":"Agricultural Production Foodgrains Coarse Cereals Volume Punjab","Value":"530"},{"Production":"Agricultural Production Foodgrains Coarse Cereals Volume Rajasthan","Value":"6910"},{"Production":"Agricultural Production Foodgrains Coarse Cereals Volume Sikkim","Value":"NA"},{"Production":"Agricultural Production Foodgrains Coarse Cereals Volume Tamil Nadu","Value":"1650"},{"Production":"Agricultural Production Foodgrains Coarse Cereals Volume Tripura","Value":"NA"},{"Production":"Agricultural Production Foodgrains Coarse Cereals Volume Union Territories","Value":"NA"},{"Production":"Agricultural Production Foodgrains Coarse Cereals Volume Uttar Pradesh","Value":"3690"},{"Production":"Agricultural Production Foodgrains Coarse Cereals Volume Uttaranchal","Value":"340"},{"Production":"Agricultural Production Foodgrains Coarse Cereals Volume West Bengal","Value":"630"},{"Production":"Agricultural Production Foodgrains Coarse Cereals Yield Andhra Pradesh","Value":"3858"},{"Production":"Agricultural Production Foodgrains Coarse Cereals Yield Bihar","Value":"3292"},{"Production":"Agricultural Production Foodgrains Coarse Cereals Yield Chhattisgarh","Value":"923"},{"Production":"Agricultural Production Foodgrains Coarse Cereals Yield Gujarat","Value":"1656"},{"Production":"Agricultural Production Foodgrains Coarse Cereals Yield Haryana","Value":"1923"},{"Production":"Agricultural Production Foodgrains Coarse Cereals Yield Himachal Pradesh","Value":"2161"},{"Production":"Agricultural Production Foodgrains Coarse Cereals Yield Jammu and Kashmir","Value":"1543"},{"Production":"Agricultural Production Foodgrains Coarse Cereals Yield Jharkhand","Value":"1640"},{"Production":"Agricultural Production Foodgrains Coarse Cereals Yield Karnataka","Value":"1713"},{"Production":"Agricultural Production Foodgrains Coarse Cereals Yield Madhya Pradesh","Value":"1543"},{"Production":"Agricultural Production Foodgrains Coarse Cereals Yield Maharashtra","Value":"930"},{"Production":"Agricultural Production Foodgrains Coarse Cereals Yield Orissa","Value":"1611"},{"Production":"Agricultural Production Foodgrains Coarse Cereals Yield Punjab","Value":"3533"},{"Production":"Agricultural Production Foodgrains Coarse Cereals Yield Rajasthan","Value":"1156"},{"Production":"Agricultural Production Foodgrains Coarse Cereals Yield Tamil Nadu","Value":"2357"},{"Production":"Agricultural Production Foodgrains Coarse Cereals Yield Uttar Pradesh","Value":"1845"},{"Production":"Agricultural Production Foodgrains Coarse Cereals Yield Uttaranchal","Value":"1360"},{"Production":"Agricultural Production Foodgrains Coarse Cereals Yield West Bengal","Value":"5250"}]